LICENSE
README.md
setup.py
ocatari/__init__.py
ocatari/core.py
ocatari/environments.py
ocatari/utils.py
ocatari.egg-info/PKG-INFO
ocatari.egg-info/SOURCES.txt
ocatari.egg-info/dependency_links.txt
ocatari.egg-info/requires.txt
ocatari.egg-info/top_level.txt
ocatari/ram/__init__.py
ocatari/ram/_helper_methods.py
ocatari/ram/adventure.py
ocatari/ram/airraid.py
ocatari/ram/alien.py
ocatari/ram/amidar.py
ocatari/ram/assault.py
ocatari/ram/asterix.py
ocatari/ram/asterix_old.py
ocatari/ram/asteroids.py
ocatari/ram/atlantis.py
ocatari/ram/bankheist.py
ocatari/ram/battlezone.py
ocatari/ram/beamrider.py
ocatari/ram/berzerk.py
ocatari/ram/bowling.py
ocatari/ram/boxing.py
ocatari/ram/breakout.py
ocatari/ram/carnival.py
ocatari/ram/centipede.py
ocatari/ram/choppercommand.py
ocatari/ram/crazyclimber.py
ocatari/ram/demonattack.py
ocatari/ram/donkeykong.py
ocatari/ram/doubledunk.py
ocatari/ram/enduro.py
ocatari/ram/extract_ram_info.py
ocatari/ram/fishingderby.py
ocatari/ram/freeway.py
ocatari/ram/frogger.py
ocatari/ram/frostbite.py
ocatari/ram/galaxian.py
ocatari/ram/game_objects.py
ocatari/ram/gopher.py
ocatari/ram/hero.py
ocatari/ram/icehockey.py
ocatari/ram/jamesbond.py
ocatari/ram/kangaroo.py
ocatari/ram/keystonekapers.py
ocatari/ram/kingkong.py
ocatari/ram/krull.py
ocatari/ram/kungfumaster.py
ocatari/ram/mariobros.py
ocatari/ram/miniaturegolf.py
ocatari/ram/montezumarevenge.py
ocatari/ram/mspacman.py
ocatari/ram/namethisgame.py
ocatari/ram/pacman.py
ocatari/ram/phoenix.py
ocatari/ram/pitfall.py
ocatari/ram/pong.py
ocatari/ram/pooyan.py
ocatari/ram/privateeye.py
ocatari/ram/qbert.py
ocatari/ram/riverraid.py
ocatari/ram/roadrunner.py
ocatari/ram/robotank.py
ocatari/ram/seaquest.py
ocatari/ram/skiing.py
ocatari/ram/spaceinvaders.py
ocatari/ram/stargunner.py
ocatari/ram/tennis.py
ocatari/ram/timepilot.py
ocatari/ram/upndown.py
ocatari/ram/utils.py
ocatari/ram/venture.py
ocatari/ram/videopinball.py
ocatari/ram/yarsrevenge.py
ocatari/vision/__init__.py
ocatari/vision/adventure.py
ocatari/vision/airraid.py
ocatari/vision/alien.py
ocatari/vision/amidar.py
ocatari/vision/assault.py
ocatari/vision/asterix.py
ocatari/vision/asteroids.py
