Metadata-Version: 2.1
Name: ocatari
Version: 2.2.1
Summary: Object Centric Atari 2600
Home-page: https://github.com/k4ntz/OC_Atari
Author: Quentin Delfosse
Author-email: quentin.delfosse@cs.tu-darmstadt.de
License: UNKNOWN
Platform: UNKNOWN
